scratchypy/__init__.py
scratchypy/color.py
scratchypy/eventcallback.py
scratchypy/image.py
scratchypy/sound.py
scratchypy/sprite.py
scratchypy/stage.py
scratchypy/text.py
scratchypy/util.py
scratchypy/version.py
scratchypy/window.py
scratchypy-0.1.2.dist-info/METADATA
scratchypy-0.1.2.dist-info/WHEEL
scratchypy-0.1.2.dist-info/licenses/LICENSE
scratchypy-0.1.2.dist-info/RECORD
