Metadata-Version: 2.1
Name: scratchypy
Version: 0.1.2
Summary: A Scratch-like library for Python using Pygame
Project-URL: Homepage, https://github.com/jtmarkoise/scratchypy
Project-URL: Issues, https://github.com/jtmarkoise/scratchypy/issues
Author: Mark Malek
License-File: LICENSE
Classifier: License :: OSI Approved :: MIT License
Classifier: Operating System :: OS Independent
Classifier: Programming Language :: Python :: 3
Requires-Python: >=3.8
Requires-Dist: pygame>=2.4.0
